{
  "dependencyLock": [
    {
      "fromPackageId": "lean-oracle-input",
      "kind": "governance.dependencyEdge.v1",
      "requires": "owner-origin-ci-secret-scope",
      "resolution": "externalOrNotYetModeled",
      "toPackageIds": []
    },
    {
      "fromPackageId": "lean-oracle-input",
      "kind": "governance.dependencyEdge.v1",
      "requires": "spec-private-input",
      "resolution": "packageId",
      "toPackageIds": [
        "spec-private-input"
      ]
    }
  ],
  "environmentBuildDefinition": {
    "kind": "governance.environmentBuildDefinition.v1",
    "officialOutput": "packages.<system>.lean-oracle-input",
    "package": "lean-oracle-input",
    "preflightRequiredTools": [
      "bash",
      "python3",
      "zip",
      "unzip",
      "git"
    ],
    "repoId": "governance-records",
    "requiredChecks": [
      {
        "missingCredentialIsFailure": true,
        "noPublicOracleRepo": true,
        "noPublicProofRepo": true,
        "oracleInputRequiresCredential": true,
        "publicBuildDoesNotFetchOracle": true
      }
    ],
    "requiredCommands": [],
    "requiredOutputs": [
      "trusted-proof-evidence-digest",
      "trusted-oracle-resolution-check",
      "release-evidence-without-proof-source"
    ],
    "runtimeRequirements": {
      "kind": "spec.runtimeRequirements.v1",
      "missingRequiredStatus": "blocked",
      "optionalForSmoke": [
        "nix",
        "jq"
      ],
      "requiredForFinal": [],
      "requiredForPreflight": [
        "bash",
        "python3",
        "zip",
        "unzip",
        "git"
      ]
    },
    "sourceOfTruth": "package-contract.v1.jsonl",
    "targetPackage": "lean-oracle-input"
  },
  "kind": "feat.input.v1",
  "packageId": "lean-oracle-input",
  "projectionDigest": "f64ea6316bc07adb81853188dad82d6e173a75fc2a66e146ab3c6f96ada08258",
  "rawAdrDirectAuthority": false,
  "repoOperation": {
    "allowedPaths": [
      "packages/lean-oracle-input/"
    ],
    "forbiddenPaths": [
      "implementation code inside specs",
      "Lean oracle source inside public specs"
    ],
    "repoSourceUri": "path:../governance-records-main",
    "targetRepoId": "governance-records"
  },
  "sourceAuthority": "governance-records-main/records/specs/package-contract.v1.jsonl",
  "specId": "pkg.lean-oracle-input",
  "status": "ready"
}
