{
  "dependencyLock": [
    {
      "fromPackageId": "qsem-dot-device-twin",
      "kind": "governance.dependencyEdge.v1",
      "requires": "qsem-schema",
      "resolution": "packageId",
      "toPackageIds": [
        "qsem-schema"
      ]
    }
  ],
  "environmentBuildDefinition": {
    "kind": "governance.environmentBuildDefinition.v1",
    "officialOutput": "packages.<system>.qsem-dot-device-twin",
    "package": "qsem-dot-device-twin",
    "preflightRequiredTools": [
      "bash",
      "python3",
      "zip",
      "unzip",
      "git"
    ],
    "repoId": "qsem-control-twin",
    "requiredChecks": [
      "checks.<system>.qsem-module-import-check",
      "checks.<system>.qsem-contract-check"
    ],
    "requiredCommands": [],
    "requiredOutputs": [
      "packages.<system>.qsem-dot-device-twin"
    ],
    "runtimeRequirements": {
      "kind": "spec.runtimeRequirements.v1",
      "missingRequiredStatus": "blocked",
      "optionalForSmoke": [
        "nix",
        "jq"
      ],
      "requiredForFinal": [],
      "requiredForPreflight": [
        "bash",
        "python3",
        "zip",
        "unzip",
        "git"
      ]
    },
    "sourceOfTruth": "package-contract.v1.jsonl",
    "targetPackage": "qsem-dot-device-twin"
  },
  "kind": "feat.input.v1",
  "packageId": "qsem-dot-device-twin",
  "projectionDigest": "16eec619f5dae732c9f1fabeae70b84f30b06fb850f39f6d5e08cbc807aba20d",
  "rawAdrDirectAuthority": false,
  "repoOperation": {
    "allowedPaths": [
      "src/qsem-dot-device-twin/"
    ],
    "forbiddenPaths": [
      "node_modules/",
      "package.json",
      "package-lock.json"
    ],
    "repoSourceUri": "local:///home/nixos/repos/qsem-control-twin",
    "targetRepoId": "qsem-control-twin"
  },
  "sourceAuthority": "governance-records-main/records/specs/package-contract.v1.jsonl",
  "specId": "pkg.qsem-dot-device-twin",
  "status": "ready"
}
